{
  "33.7743_-84.3959": "704 Cherry Street Northwest, Atlanta, Georgia",
  "33.7743_-84.3958": "704 Cherry Street Northwest, Atlanta, Georgia",
  "37.7742_-122.4185": "49 South Van Ness Avenue, Hayes Valley, San Francisco",
  "37.7749_-122.4194": "South Van Ness Avenue, San Francisco, California",
  "38.5816_-121.4944": "900 9th Street, Downtown, Sacramento",
  "37.776_-122.4205": "155 Fell Street, Civic Center, San Francisco",
  "34.0522_-118.2437": "West 1st Street, Downtown, Los Angeles",
  "32.7157_-117.1611": "326 Broadway, Marina, San Diego",
  "37.3382_-121.8863": "223 East Santa Clara Street, Horace Mann, San Jose",
  "37.7755_-122.42": "Oak Street, Civic Center, San Francisco",
  "37.7753_-122.4199": "1540 Market Street, Hayes Valley, San Francisco",
  "37.7755_-122.41": "13th Street, Mission District, San Francisco",
  "34.0528_-118.245": "West 1st Street, Downtown, Los Angeles",
  "37.7755_-120.42": "California",
  "37.7752_-122.4196": "Market Street, Hayes Valley, San Francisco",
  "37.7599_-122.4148": "2335;2337 Folsom Street, Mission District, San Francisco",
  "37.7749_-122.4094": "13th Street, Mission District, San Francisco",
  "34.0928_-118.3287": "North Cahuenga Boulevard, Hollywood, Los Angeles",
  "38.5825_-121.4952": "I Street, Downtown, Sacramento",
  "34.0527_-118.2447": "137 South Spring Street, Downtown, Los Angeles",
  "37.775_-122.4198": "Market Street, Hayes Valley, San Francisco",
  "37.7748_-122.4192": "10 South Van Ness Avenue, San Francisco, California",
  "37.7699_-122.4344": "53 Carmelita Street, Duboce Triangle, San Francisco",
  "37.7743_-122.4088": "13th Street, Mission District, San Francisco",
  "34.053_-118.2445": "201 West 1st Street, Downtown, Los Angeles",
  "38.581_-121.4935": "948 10th Street, Downtown, Sacramento",
  "37.339_-121.887": "North 5th Street, Horace Mann, San Jose",
  "37.7756_-122.4203": "50 Oak Street, Civic Center, San Francisco",
  "37.7941_-122.4078": "857;863 Clay Street, San Francisco, California",
  "37.7948_-122.4085": "950 Clay Street, San Francisco, California",
  "34.0935_-118.3295": "6415 La Mirada Avenue, Hollywood, Los Angeles",
  "32.7165_-117.162": "1088 3rd Avenue, Core-Columbia, San Diego",
  "37.3375_-121.8855": "San José Civic Plaza, Horace Mann, San Jose",
  "34.0525_-118.244": "150 West 1st Street, Downtown, Los Angeles",
  "37.7746_-122.4188": "11 South Van Ness Avenue, Hayes Valley, San Francisco",
  "37.8067_-122.4094": "North Point Street, San Francisco, California"
}